jetto_tools/__init__.py
jetto_tools/_utils.py
jetto_tools/binary.py
jetto_tools/catalog.py
jetto_tools/classes.py
jetto_tools/coconut-to-jetto.py
jetto_tools/common.py
jetto_tools/config.py
jetto_tools/convert_jsp_to_exfile_config.json
jetto_tools/graydata.py
jetto_tools/jams.py
jetto_tools/jintrac.py
jetto_tools/job.py
jetto_tools/jset.py
jetto_tools/lookup.py
jetto_tools/mast_jetto_tools.py
jetto_tools/matlab.py
jetto_tools/misc.py
jetto_tools/namelist.py
jetto_tools/nested_dicts.py
jetto_tools/output_to_input.py
jetto_tools/plot_growthrates_TCI.py
jetto_tools/qualikiz.py
jetto_tools/raptor.py
jetto_tools/results.py
jetto_tools/results_gui.py
jetto_tools/run.py
jetto_tools/set-exfile-profiles.py
jetto_tools/settings.py
jetto_tools/setup_logging.py
jetto_tools/template.py
jetto_tools/tglf-dump-parameter-space.py
jetto_tools/time-dependent-boundary-condition.py
jetto_tools/tkinter_helpers.py
jetto_tools/transp.py
jetto_tools/turb_analysis.py
jetto_tools/version.py
jetto_tools/analysis/__init__.py
jetto_tools/analysis/gray.py
jetto_tools/templates/exfile.json
jetto_tools/templates/jpyplot.mplstyle
jetto_tools-2.2.0.data/scripts/convert_jsp_jst_to_transp.py
jetto_tools-2.2.0.data/scripts/convert_jsp_to_ex.py
jetto_tools-2.2.0.data/scripts/convert_transp_to_exfile.py
jetto_tools-2.2.0.data/scripts/qlk_timetrace.py
jetto_tools-2.2.0.dist-info/licenses/LICENSE
jetto_tools-2.2.0.dist-info/METADATA
jetto_tools-2.2.0.dist-info/WHEEL
jetto_tools-2.2.0.dist-info/entry_points.txt
jetto_tools-2.2.0.dist-info/top_level.txt
jetto_tools-2.2.0.dist-info/RECORD
