Metadata-Version: 2.4
Name: jetto_tools
Version: 2.2.0
Summary: Tools for plotting and manipulating JETTO runs.
Home-page: https://gitlab.com/jintrac/jetto-pythontools
Author: Karel van de Plassche
Author-email: k.l.vandeplassche@differ.nl
License: MIT
Classifier: Intended Audience :: Developers
Classifier: Intended Audience :: Science/Research
Classifier: License :: OSI Approved :: MIT License
Classifier: Programming Language :: Python :: 3
Classifier: Natural Language :: English
Classifier: Topic :: Utilities
Requires-Python: >=3.6
License-File: LICENSE
Requires-Dist: numpy>=1.15.4
Requires-Dist: scipy!=1.9,>=1.1.0
Requires-Dist: ipython>=7.2.0
Requires-Dist: pandas>=0.23.4
Requires-Dist: xarray>=0.13.0
Requires-Dist: f90nml>=1.2
Requires-Dist: cerberus>=1.3.2
Requires-Dist: prominence>=0.16.0
Requires-Dist: docker>=6.0.1
Requires-Dist: netCDF4>=1.4.2
Requires-Dist: matplotlib>=3.0.2
Provides-Extra: test
Requires-Dist: coverage; extra == "test"
Requires-Dist: pytest>=4.6; extra == "test"
Requires-Dist: pytest-cov>=0.6; extra == "test"
Requires-Dist: pytest-mock>=3.3.1; extra == "test"
Requires-Dist: pytest-subprocess>=1.0.0; extra == "test"
Provides-Extra: gui
Requires-Dist: tkfilebrowser; extra == "gui"
Requires-Dist: tkcolorpicker; extra == "gui"
Provides-Extra: docs
Requires-Dist: sphinx>=3.2.1; extra == "docs"
Requires-Dist: sphinx_rtd_theme>=0.5; extra == "docs"
Requires-Dist: recommonmark>=0.6; extra == "docs"
Requires-Dist: sphinx-autosummary-accessors>=0.1.2; extra == "docs"
Provides-Extra: all
Requires-Dist: coverage; extra == "all"
Requires-Dist: pytest>=4.6; extra == "all"
Requires-Dist: pytest-cov>=0.6; extra == "all"
Requires-Dist: pytest-mock>=3.3.1; extra == "all"
Requires-Dist: pytest-subprocess>=1.0.0; extra == "all"
Requires-Dist: tkfilebrowser; extra == "all"
Requires-Dist: tkcolorpicker; extra == "all"
Requires-Dist: sphinx>=3.2.1; extra == "all"
Requires-Dist: sphinx_rtd_theme>=0.5; extra == "all"
Requires-Dist: recommonmark>=0.6; extra == "all"
Requires-Dist: sphinx-autosummary-accessors>=0.1.2; extra == "all"
Dynamic: author
Dynamic: author-email
Dynamic: classifier
Dynamic: description
Dynamic: description-content-type
Dynamic: home-page
Dynamic: license
Dynamic: license-file
Dynamic: provides-extra
Dynamic: requires-dist
Dynamic: requires-python
Dynamic: summary
